{
    "$schema": "https://schema.management.azure.com/schemas/2015-01-01/deploymentTemplate.json#",
    "contentVersion": "1.0.0.0",
    "parameters": {},
    "variables": {},
    "resources": [
        {
            "type": "Microsoft.Network/networkSecurityGroups",
            "apiVersion": "2020-04-01",
            "name": "NSG-01",
            "location": "eastus2",
            "properties": {
                "securityRules": [
                    {
                        "name": "Allow_RDP_Port_3389",
                        "properties": {
                            "description": "Libera acesso remoto via RDP.",
                            "protocol": "TCP",
                            "sourcePortRange": "*",
                            "destinationPortRange": "3389",
                            "sourceAddressPrefix": "*",
                            "destinationAddressPrefix": "VirtualNetwork",
                            "access": "Allow",
                            "priority": 100,
                            "direction": "Inbound",
                            "sourcePortRanges": [],
                            "destinationPortRanges": [],
                            "sourceAddressPrefixes": [],
                            "destinationAddressPrefixes": []
                        }
                    }
                ]
            }
        },
        {
            "type": "Microsoft.Network/publicIPAddresses",
            "apiVersion": "2020-04-01",
            "name": "SRV-01-ip",
            "location": "eastus2",
            "sku": {
                "name": "Basic"
            },
            "properties": {
                "ipAddress": "52.254.5.123",
                "publicIPAddressVersion": "IPv4",
                "publicIPAllocationMethod": "Dynamic",
                "idleTimeoutInMinutes": 4,
                "ipTags": []
            }
        },
        {
            "type": "Microsoft.Network/publicIPAddresses",
            "apiVersion": "2020-04-01",
            "name": "SRV02ip211",
            "location": "eastus2",
            "sku": {
                "name": "Basic"
            },
            "properties": {
                "ipAddress": "52.138.82.24",
                "publicIPAddressVersion": "IPv4",
                "publicIPAllocationMethod": "Dynamic",
                "idleTimeoutInMinutes": 4,
                "ipTags": []
            }
        },
        {
            "type": "Microsoft.Compute/virtualMachines",
            "apiVersion": "2019-07-01",
            "name": "SRV-01",
            "location": "eastus2",
            "dependsOn": [
                "[resourceId('Microsoft.Network/networkInterfaces', 'srv-01379')]"
            ],
            "properties": {
                "hardwareProfile": {
                    "vmSize": "Standard_B2s"
                },
                "storageProfile": {
                    "imageReference": {
                        "publisher": "MicrosoftWindowsServer",
                        "offer": "WindowsServer",
                        "sku": "2019-Datacenter",
                        "version": "latest"
                    },
                    "osDisk": {
                        "osType": "Windows",
                        "name": "SRV-01_OsDisk_1_ffe4326cc1bf4763bccb2c630365730a",
                        "createOption": "FromImage",
                        "caching": "ReadWrite",
                        "managedDisk": {
                            "storageAccountType": "StandardSSD_LRS",
                            "id": "[resourceId('Microsoft.Compute/disks', 'SRV-01_OsDisk_1_ffe4326cc1bf4763bccb2c630365730a')]"
                        },
                        "diskSizeGB": 127
                    },
                    "dataDisks": []
                },
                "osProfile": {
                    "computerName": "SRV-01",
                    "adminUsername": "adminazure",
                    "windowsConfiguration": {
                        "provisionVMAgent": true,
                        "enableAutomaticUpdates": true
                    },
                    "secrets": [],
                    "allowExtensionOperations": true,
                    "requireGuestProvisionSignal": true
                },
                "networkProfile": {
                    "networkInterfaces": [
                        {
                            "id": "[resourceId('Microsoft.Network/networkInterfaces', 'srv-01379')]"
                        }
                    ]
                }
            }
        },
        {
            "type": "Microsoft.Compute/virtualMachines",
            "apiVersion": "2019-07-01",
            "name": "SRV-02",
            "location": "eastus2",
            "dependsOn": [
                "[resourceId('Microsoft.Network/networkInterfaces', 'srv-02968')]"
            ],
            "properties": {
                "hardwareProfile": {
                    "vmSize": "Standard_B2s"
                },
                "storageProfile": {
                    "imageReference": {
                        "publisher": "MicrosoftWindowsServer",
                        "offer": "WindowsServer",
                        "sku": "2019-Datacenter",
                        "version": "latest"
                    },
                    "osDisk": {
                        "osType": "Windows",
                        "name": "SRV-02_OsDisk_1_f77b2954fdae4399a247fff9d5ce7889",
                        "createOption": "FromImage",
                        "caching": "ReadWrite",
                        "managedDisk": {
                            "storageAccountType": "StandardSSD_LRS",
                            "id": "[resourceId('Microsoft.Compute/disks', 'SRV-02_OsDisk_1_f77b2954fdae4399a247fff9d5ce7889')]"
                        },
                        "diskSizeGB": 127
                    },
                    "dataDisks": []
                },
                "osProfile": {
                    "computerName": "SRV-02",
                    "adminUsername": "adminazure",
                    "windowsConfiguration": {
                        "provisionVMAgent": true,
                        "enableAutomaticUpdates": true
                    },
                    "secrets": [],
                    "allowExtensionOperations": true,
                    "requireGuestProvisionSignal": true
                },
                "networkProfile": {
                    "networkInterfaces": [
                        {
                            "id": "[resourceId('Microsoft.Network/networkInterfaces', 'srv-02968')]"
                        }
                    ]
                }
            }
        },
        {
            "type": "microsoft.devtestlab/schedules",
            "apiVersion": "2018-09-15",
            "name": "shutdown-computevm-srv-01",
            "location": "eastus2",
            "dependsOn": [
                "[resourceId('Microsoft.Compute/virtualMachines', 'SRV-01')]"
            ],
            "properties": {
                "status": "Enabled",
                "taskType": "ComputeVmShutdownTask",
                "dailyRecurrence": {
                    "time": "2300"
                },
                "timeZoneId": "E. South America Standard Time",
                "notificationSettings": {
                    "status": "Enabled",
                    "timeInMinutes": 30,
                    "emailRecipient": "rodrigo_greff@hotmail.com",
                    "notificationLocale": "en"
                },
                "targetResourceId": "[resourceId('Microsoft.Compute/virtualMachines', 'SRV-01')]"
            }
        },
        {
            "type": "microsoft.devtestlab/schedules",
            "apiVersion": "2018-09-15",
            "name": "shutdown-computevm-srv-02",
            "location": "eastus2",
            "dependsOn": [
                "[resourceId('Microsoft.Compute/virtualMachines', 'SRV-02')]"
            ],
            "properties": {
                "status": "Enabled",
                "taskType": "ComputeVmShutdownTask",
                "dailyRecurrence": {
                    "time": "2300"
                },
                "timeZoneId": "E. South America Standard Time",
                "notificationSettings": {
                    "status": "Enabled",
                    "timeInMinutes": 30,
                    "emailRecipient": "rodrigo_greff@hotmail.com",
                    "notificationLocale": "en"
                },
                "targetResourceId": "[resourceId('Microsoft.Compute/virtualMachines', 'SRV-02')]"
            }
        },
        {
            "type": "Microsoft.Network/networkSecurityGroups/securityRules",
            "apiVersion": "2020-04-01",
            "name": "NSG-01/Allow_RDP_Port_3389",
            "dependsOn": [
                "[resourceId('Microsoft.Network/networkSecurityGroups', 'NSG-01')]"
            ],
            "properties": {
                "description": "Libera acesso remoto via RDP.",
                "protocol": "TCP",
                "sourcePortRange": "*",
                "destinationPortRange": "3389",
                "sourceAddressPrefix": "*",
                "destinationAddressPrefix": "VirtualNetwork",
                "access": "Allow",
                "priority": 100,
                "direction": "Inbound",
                "sourcePortRanges": [],
                "destinationPortRanges": [],
                "sourceAddressPrefixes": [],
                "destinationAddressPrefixes": []
            }
        },
        {
            "type": "Microsoft.Network/virtualNetworks",
            "apiVersion": "2020-04-01",
            "name": "VNET-01",
            "location": "eastus2",
            "dependsOn": [
                "[resourceId('Microsoft.Network/networkSecurityGroups', 'NSG-01')]"
            ],
            "tags": {
                "Ambiente": "Produção"
            },
            "properties": {
                "addressSpace": {
                    "addressPrefixes": [
                        "172.16.0.0/16"
                    ]
                },
                "subnets": [
                    {
                        "name": "SUB-01",
                        "properties": {
                            "addressPrefix": "172.16.1.0/24",
                            "networkSecurityGroup": {
                                "id": "[resourceId('Microsoft.Network/networkSecurityGroups', 'NSG-01')]"
                            },
                            "delegations": [],
                            "privateEndpointNetworkPolicies": "Enabled",
                            "privateLinkServiceNetworkPolicies": "Enabled"
                        }
                    }
                ],
                "virtualNetworkPeerings": [],
                "enableDdosProtection": false,
                "enableVmProtection": false
            }
        },
        {
            "type": "Microsoft.Network/networkInterfaces",
            "apiVersion": "2020-04-01",
            "name": "srv-01379",
            "location": "eastus2",
            "dependsOn": [
                "[resourceId('Microsoft.Network/publicIPAddresses', 'SRV-01-ip')]",
                "[resourceId('Microsoft.Network/virtualNetworks/subnets', 'VNET-01', 'SUB-01')]"
            ],
            "properties": {
                "ipConfigurations": [
                    {
                        "name": "ipconfig1",
                        "properties": {
                            "privateIPAddress": "172.16.1.4",
                            "privateIPAllocationMethod": "Dynamic",
                            "publicIPAddress": {
                                "id": "[resourceId('Microsoft.Network/publicIPAddresses', 'SRV-01-ip')]"
                            },
                            "subnet": {
                                "id": "[resourceId('Microsoft.Network/virtualNetworks/subnets', 'VNET-01', 'SUB-01')]"
                            },
                            "primary": true,
                            "privateIPAddressVersion": "IPv4"
                        }
                    }
                ],
                "dnsSettings": {
                    "dnsServers": []
                },
                "enableAcceleratedNetworking": false,
                "enableIPForwarding": false
            }
        },
        {
            "type": "Microsoft.Network/networkInterfaces",
            "apiVersion": "2020-04-01",
            "name": "srv-02968",
            "location": "eastus2",
            "dependsOn": [
                "[resourceId('Microsoft.Network/publicIPAddresses', 'SRV02ip211')]",
                "[resourceId('Microsoft.Network/virtualNetworks/subnets', 'VNET-01', 'SUB-01')]"
            ],
            "properties": {
                "ipConfigurations": [
                    {
                        "name": "ipconfig1",
                        "properties": {
                            "privateIPAddress": "172.16.1.5",
                            "privateIPAllocationMethod": "Dynamic",
                            "publicIPAddress": {
                                "id": "[resourceId('Microsoft.Network/publicIPAddresses', 'SRV02ip211')]"
                            },
                            "subnet": {
                                "id": "[resourceId('Microsoft.Network/virtualNetworks/subnets', 'VNET-01', 'SUB-01')]"
                            },
                            "primary": true,
                            "privateIPAddressVersion": "IPv4"
                        }
                    }
                ],
                "dnsSettings": {
                    "dnsServers": []
                },
                "enableAcceleratedNetworking": false,
                "enableIPForwarding": false
            }
        },
        {
            "type": "Microsoft.Network/virtualNetworks/subnets",
            "apiVersion": "2020-04-01",
            "name": "VNET-01/SUB-01",
            "dependsOn": [
                "[resourceId('Microsoft.Network/virtualNetworks', 'VNET-01')]",
                "[resourceId('Microsoft.Network/networkSecurityGroups', 'NSG-01')]"
            ],
            "properties": {
                "addressPrefix": "172.16.1.0/24",
                "networkSecurityGroup": {
                    "id": "[resourceId('Microsoft.Network/networkSecurityGroups', 'NSG-01')]"
                },
                "delegations": [],
                "privateEndpointNetworkPolicies": "Enabled",
                "privateLinkServiceNetworkPolicies": "Enabled"
            }
        }
    ]
}